Metadata-Version: 2.4
Name: iflow-mcp_scrapegraph-mcp
Version: 1.0.0
Summary: MCP server for ScapeGraph API integration
Project-URL: Homepage, https://github.com/ScrapeGraphAI/scrapegraph-mcp
Project-URL: Bug Tracker, https://github.com/ScrapeGraphAI/scrapegraph-mcp/issues
Author-email: Marco Perini <marco.perini@scrapegraphai.com>
License: MIT
License-File: LICENSE
Classifier: Development Status :: 4 - Beta
Classifier: Intended Audience :: Developers
Classifier: License :: OSI Approved :: MIT License
Classifier: Programming Language :: Python :: 3
Classifier: Programming Language :: Python :: 3.10
Classifier: Topic :: Software Development :: Libraries :: Python Modules
Requires-Python: >=3.10
Requires-Dist: fastmcp>=2.0.0
Requires-Dist: httpx>=0.24.0
Requires-Dist: pydantic>=2.0.0
Requires-Dist: smithery>=0.4.2
Requires-Dist: uvicorn>=0.27.0
Provides-Extra: dev
Requires-Dist: mypy>=1.0.0; extra == 'dev'
Requires-Dist: ruff>=0.1.0; extra == 'dev'
